odoo/addons/product_model_viewer/README.rst
odoo/addons/product_model_viewer/__init__.py
odoo/addons/product_model_viewer/__manifest__.py
odoo/addons/product_model_viewer/data/product_demo.xml
odoo/addons/product_model_viewer/i18n/ca.po
odoo/addons/product_model_viewer/i18n/es.po
odoo/addons/product_model_viewer/i18n/product_model_viewer.pot
odoo/addons/product_model_viewer/models/__init__.py
odoo/addons/product_model_viewer/models/product.py
odoo/addons/product_model_viewer/readme/CONTRIBUTORS.rst
odoo/addons/product_model_viewer/readme/DESCRIPTION.rst
odoo/addons/product_model_viewer/readme/USAGE.rst
odoo/addons/product_model_viewer/static/description/icon.png
odoo/addons/product_model_viewer/static/description/index.html
odoo/addons/product_model_viewer/tests/__init__.py
odoo/addons/product_model_viewer/tests/test_model_viewer.py
odoo/addons/product_model_viewer/views/product_views.xml
odoo12_addon_product_model_viewer-12.0.1.0.2.dist-info/METADATA
odoo12_addon_product_model_viewer-12.0.1.0.2.dist-info/WHEEL
odoo12_addon_product_model_viewer-12.0.1.0.2.dist-info/top_level.txt
odoo12_addon_product_model_viewer-12.0.1.0.2.dist-info/RECORD
