Metadata-Version: 2.1
Name: odoo12-addon-product-model-viewer
Version: 12.0.1.0.2
Summary: 3D model viewer for products
Home-page: https://github.com/OCA/product-attribute
Author: TAKOBI, Openindustry.it, Odoo Community Association (OCA)
Author-email: support@odoo-community.org
License: AGPL-3
Platform: UNKNOWN
Classifier: Programming Language :: Python
Classifier: Framework :: Odoo
Classifier: Framework :: Odoo :: 12.0
Classifier: License :: OSI Approved :: GNU Affero General Public License v3
Classifier: Development Status :: 4 - Beta
Requires-Python: >=3.5
Requires-Dist: odoo12-addon-web-widget-model-viewer
Requires-Dist: odoo (<12.1dev,>=12.0a)
